{
  "version": "7",
  "dialect": "sqlite",
  "entries": [
    {
      "idx": 0,
      "version": "6",
      "when": 1777869136015,
      "tag": "0000_panoramic_grim_reaper",
      "breakpoints": true
    },
    {
      "idx": 1,
      "version": "6",
      "when": 1777870706541,
      "tag": "0001_tan_zaran",
      "breakpoints": true
    },
    {
      "idx": 2,
      "version": "6",
      "when": 1777873384011,
      "tag": "0002_dizzy_pepper_potts",
      "breakpoints": true
    },
    {
      "idx": 3,
      "version": "6",
      "when": 1777942101783,
      "tag": "0003_long_agent_zero",
      "breakpoints": true
    }
  ]
}